[
    {
        "id": "372_冬天",
        "pos": "m.",
        "word": "invierno",
        "definition": "195页",
        "translation": "m. 冬天",
        "voiceUrl": "modernSpanish/modernSpanish_113/372_冬天.mp3"
    },
    {
        "id": "373_农村田野",
        "pos": "m.",
        "word": "campo",
        "definition": "195页",
        "translation": "m. 农村，田野",
        "voiceUrl": "modernSpanish/modernSpanish_113/373_农村田野.mp3"
    },
    {
        "id": "374_中级的",
        "pos": "adj.",
        "word": "secundario",
        "definition": "195页",
        "translation": "adj. 中级的",
        "voiceUrl": "modernSpanish/modernSpanish_113/374_中级的.mp3"
    },
    {
        "id": "375_起床",
        "pos": "prnl.",
        "word": "levantarse",
        "definition": "195页",
        "translation": "prnl. 起床",
        "voiceUrl": "modernSpanish/modernSpanish_113/375_起床.mp3"
    },
    {
        "id": "376_穿衣",
        "pos": "prnl.",
        "word": "vestirse",
        "definition": "195页",
        "translation": "prnl. 穿衣",
        "voiceUrl": "modernSpanish/modernSpanish_113/376_穿衣.mp3"
    },
    {
        "id": "377_整理床铺",
        "pos": null,
        "word": "hacer la cama",
        "definition": "195页",
        "translation": "整理床铺",
        "voiceUrl": "modernSpanish/modernSpanish_113/377_整理床铺.mp3"
    },
    {
        "id": "378_洗漱",
        "pos": "prnl.",
        "word": "asearse",
        "definition": "195页",
        "translation": "prnl. 洗漱",
        "voiceUrl": "modernSpanish/modernSpanish_113/378_洗漱.mp3"
    },
    {
        "id": "379_快",
        "pos": "adv.",
        "word": "rápido",
        "definition": "195页",
        "translation": "adv. 快",
        "voiceUrl": "modernSpanish/modernSpanish_113/379_快.mp3"
    },
    {
        "id": "380_进入",
        "pos": "intr.",
        "word": "entrar",
        "definition": "195页",
        "translation": "intr. 进入",
        "voiceUrl": "modernSpanish/modernSpanish_113/380_进入.mp3"
    },
    {
        "id": "381_开始",
        "pos": "tr.",
        "word": "empezar",
        "definition": "195页",
        "translation": "tr. 开始",
        "voiceUrl": "modernSpanish/modernSpanish_113/381_开始.mp3"
    },
    {
        "id": "382_准备",
        "pos": "tr.",
        "word": "preparar",
        "definition": "195页",
        "translation": "tr. 准备",
        "voiceUrl": "modernSpanish/modernSpanish_113/382_准备.mp3"
    },
    {
        "id": "383_早饭",
        "pos": "m.",
        "word": "desayuno",
        "definition": "195页",
        "translation": "m. 早饭",
        "voiceUrl": "modernSpanish/modernSpanish_113/383_早饭.mp3"
    },
    {
        "id": "384_忙于做某事",
        "pos": "prnl.",
        "word": "ocuparse",
        "definition": "195页",
        "translation": "prnl. 忙于（做某事）",
        "voiceUrl": "modernSpanish/modernSpanish_113/384_忙于做某事.mp3"
    },
    {
        "id": "385_打扫清洁",
        "pos": "tr.",
        "word": "limpiar",
        "definition": "195页",
        "translation": "tr. 打扫，清洁",
        "voiceUrl": "modernSpanish/modernSpanish_113/385_打扫清洁.mp3"
    },
    {
        "id": "386_另一个",
        "pos": "adj.",
        "word": "otro",
        "definition": "195页",
        "translation": "adj. 另一个",
        "voiceUrl": "modernSpanish/modernSpanish_113/386_另一个.mp3"
    },
    {
        "id": "387_停当好了",
        "pos": "adj.",
        "word": "listo",
        "definition": "195页",
        "translation": "adj. 停当，好了",
        "voiceUrl": "modernSpanish/modernSpanish_113/387_停当好了.mp3"
    },
    {
        "id": "388_叫醒",
        "pos": "tr.",
        "word": "despertar",
        "definition": "195页",
        "translation": "tr. 叫醒",
        "voiceUrl": "modernSpanish/modernSpanish_113/388_叫醒.mp3"
    },
    {
        "id": "389_吃早饭",
        "pos": "intr.",
        "word": "desayunar",
        "definition": "195页",
        "translation": "intr. 吃早饭",
        "voiceUrl": "modernSpanish/modernSpanish_113/389_吃早饭.mp3"
    },
    {
        "id": "390_离开出去",
        "pos": "tr.",
        "word": "salir",
        "definition": "195页",
        "translation": "tr. 离开，出去",
        "voiceUrl": "modernSpanish/modernSpanish_113/390_离开出去.mp3"
    },
    {
        "id": "391_吃午饭",
        "pos": "adj.",
        "word": "almorzar",
        "definition": "195页",
        "translation": "adj. 吃午饭",
        "voiceUrl": "modernSpanish/modernSpanish_113/391_吃午饭.mp3"
    },
    {
        "id": "392_一起",
        "pos": "adj.",
        "word": "junto",
        "definition": "195页",
        "translation": "adj. 一起",
        "voiceUrl": "modernSpanish/modernSpanish_113/392_一起.mp3"
    },
    {
        "id": "393_回来返回",
        "pos": "intr.",
        "word": "regresar",
        "definition": "195页",
        "translation": "intr. 回来，返回",
        "voiceUrl": "modernSpanish/modernSpanish_113/393_回来返回.mp3"
    },
    {
        "id": "394_直到",
        "pos": "prep.",
        "word": "hasta",
        "definition": "196页",
        "translation": "prep. 直到",
        "voiceUrl": "modernSpanish/modernSpanish_113/394_直到.mp3"
    },
    {
        "id": "395_会集聚集",
        "pos": "prnl.",
        "word": "reunirse",
        "definition": "196页",
        "translation": "prnl. 会集，聚集",
        "voiceUrl": "modernSpanish/modernSpanish_113/395_会集聚集.mp3"
    },
    {
        "id": "396_吃晚饭",
        "pos": "tr.",
        "word": "cenar",
        "definition": "196页",
        "translation": "tr. 吃晚饭",
        "voiceUrl": "modernSpanish/modernSpanish_113/396_吃晚饭.mp3"
    },
    {
        "id": "397_电视",
        "pos": "f.",
        "word": "televisión",
        "definition": "196页",
        "translation": "f. 电视",
        "voiceUrl": "modernSpanish/modernSpanish_113/397_电视.mp3"
    },
    {
        "id": "398_有许多事情要做",
        "pos": null,
        "word": "tener mucho que hacer",
        "definition": "196页",
        "translation": "有许多事情要做",
        "voiceUrl": "modernSpanish/modernSpanish_113/398_有许多事情要做.mp3"
    },
    {
        "id": "399_永远总是",
        "pos": "adv.",
        "word": "siempre",
        "definition": "196页",
        "translation": "adv. 永远，总是",
        "voiceUrl": "modernSpanish/modernSpanish_113/399_永远总是.mp3"
    },
    {
        "id": "400_忙碌忙于",
        "pos": "p.p.",
        "word": "ocupado",
        "definition": "196页",
        "translation": "p.p. 忙碌，忙于",
        "voiceUrl": "modernSpanish/modernSpanish_113/400_忙碌忙于.mp3"
    },
    {
        "id": "401_淋浴",
        "pos": "prnl.",
        "word": "ducharse",
        "definition": "196页",
        "translation": "prnl. 淋浴",
        "voiceUrl": "modernSpanish/modernSpanish_113/401_淋浴.mp3"
    },
    {
        "id": "402_半夜",
        "pos": "f.",
        "word": "medianoche",
        "definition": "196页",
        "translation": "f. 半夜",
        "voiceUrl": "modernSpanish/modernSpanish_113/402_半夜.mp3"
    },
    {
        "id": "403_上床",
        "pos": "prnl.",
        "word": "acostarse",
        "definition": "196页",
        "translation": "prnl. 上床",
        "voiceUrl": "modernSpanish/modernSpanish_113/403_上床.mp3"
    },
    {
        "id": "404_想",
        "pos": "tr.",
        "word": "pensar",
        "definition": "196页",
        "translation": "tr. 想",
        "voiceUrl": "modernSpanish/modernSpanish_113/404_想.mp3"
    },
    {
        "id": "405_帮助",
        "pos": "tr.",
        "word": "ayudar",
        "definition": "196页",
        "translation": "tr. 帮助",
        "voiceUrl": "modernSpanish/modernSpanish_113/405_帮助.mp3"
    },
    {
        "id": "406_事情家务",
        "pos": "m.",
        "word": "quehacer",
        "definition": "196页",
        "translation": "m. 事情，家务",
        "voiceUrl": "modernSpanish/modernSpanish_113/406_事情家务.mp3"
    },
    {
        "id": "407_不仅而且",
        "pos": null,
        "word": "no sólo ...sino también",
        "definition": "196页",
        "translation": "不仅……而且",
        "voiceUrl": "modernSpanish/modernSpanish_113/407_不仅而且.mp3"
    },
    {
        "id": "408_如此这样",
        "pos": "adv.",
        "word": "tanto",
        "definition": "196页",
        "translation": "adv. 如此，这样",
        "voiceUrl": "modernSpanish/modernSpanish_113/408_如此这样.mp3"
    },
    {
        "id": "409_企业家",
        "pos": "m.,f.",
        "word": "empresario,ria",
        "definition": "196页",
        "translation": "m.,f. 企业家",
        "voiceUrl": "modernSpanish/modernSpanish_113/409_企业家.mp3"
    },
    {
        "id": "410_家庭主妇",
        "pos": null,
        "word": "ama de casa",
        "definition": "196页",
        "translation": "家庭主妇",
        "voiceUrl": "modernSpanish/modernSpanish_113/410_家庭主妇.mp3"
    },
    {
        "id": "411_确实的",
        "pos": "adj.",
        "word": "cierto",
        "definition": "196页",
        "translation": "adj. 确实的",
        "voiceUrl": "modernSpanish/modernSpanish_113/411_确实的.mp3"
    },
    {
        "id": "412_哪里哪哟",
        "pos": null,
        "word": "qué va",
        "definition": "196页",
        "translation": "哪里，哪哟",
        "voiceUrl": "modernSpanish/modernSpanish_113/412_哪里哪哟.mp3"
    },
    {
        "id": "413_于是那么",
        "pos": "adv.",
        "word": "entonces",
        "definition": "196页",
        "translation": "adv. 于是，那么",
        "voiceUrl": "modernSpanish/modernSpanish_113/413_于是那么.mp3"
    },
    {
        "id": "414_比谁都早",
        "pos": null,
        "word": "antes que nadie",
        "definition": "196页",
        "translation": "比（谁）都早",
        "voiceUrl": "modernSpanish/modernSpanish_113/414_比谁都早.mp3"
    },
    {
        "id": "415_肯定保准",
        "pos": "adv.",
        "word": "seguro",
        "definition": "196页",
        "translation": "adv. 肯定，保准",
        "voiceUrl": "modernSpanish/modernSpanish_113/415_肯定保准.mp3"
    },
    {
        "id": "416_确实如此",
        "pos": "adv.",
        "word": "efectivamente",
        "definition": "196页",
        "translation": "adv. 确实如此",
        "voiceUrl": "modernSpanish/modernSpanish_113/416_确实如此.mp3"
    },
    {
        "id": "417_这样",
        "pos": "adv.",
        "word": "así",
        "definition": "196页",
        "translation": "adv. 这样",
        "voiceUrl": "modernSpanish/modernSpanish_113/417_这样.mp3"
    }
]